{
  "db_name": "PostgreSQL",
  "query": "SELECT * FROM packages WHERE id = $1 FOR UPDATE;",
  "describe": {
    "columns": [
      {
        "ordinal": 0,
        "name": "id",
        "type_info": "Text"
      },
      {
        "ordinal": 1,
        "name": "name",
        "type_info": "Text"
      },
      {
        "ordinal": 2,
        "name": "version",
        "type_info": "Text"
      },
      {
        "ordinal": 3,
        "name": "downloads",
        "type_info": "Int8"
      }
    ],
    "parameters": {
      "Left": [
        "Text"
      ]
    },
    "nullable": [
      false,
      false,
      false,
      false
    ]
  },
  "hash": "75d50585c88b5e6faf5e6086ffed3166d134060a920c1be53dc5c06cdcaf3de3"
}
